commonkit/__init__.py
commonkit/compat.py
commonkit/constants.py
commonkit/version.py
commonkit/config/__init__.py
commonkit/config/base.py
commonkit/config/exceptions.py
commonkit/config/flat.py
commonkit/config/ini.py
commonkit/config/py.py
commonkit/context_managers/__init__.py
commonkit/context_managers/library.py
commonkit/csv/__init__.py
commonkit/csv/library.py
commonkit/database/__init__.py
commonkit/database/compat.py
commonkit/database/constants.py
commonkit/database/exceptions.py
commonkit/database/factory.py
commonkit/database/library.py
commonkit/database/backends/__init__.py
commonkit/database/backends/base.py
commonkit/database/backends/mssql.py
commonkit/database/backends/mysql.py
commonkit/database/backends/oracle.py
commonkit/database/backends/pgsql.py
commonkit/database/backends/sqlite.py
commonkit/dispatcher/__init__.py
commonkit/dispatcher/library.py
commonkit/exceptions/__init__.py
commonkit/exceptions/library.py
commonkit/files/__init__.py
commonkit/files/library.py
commonkit/lists/__init__.py
commonkit/lists/library.py
commonkit/loading/__init__.py
commonkit/loading/library.py
commonkit/logging/__init__.py
commonkit/logging/library.py
commonkit/math/__init__.py
commonkit/math/library.py
commonkit/platform/__init__.py
commonkit/platform/library.py
commonkit/pluggable/__init__.py
commonkit/pluggable/library.py
commonkit/regex/__init__.py
commonkit/regex/patterns.py
commonkit/shell/__init__.py
commonkit/shell/commands.py
commonkit/shell/constants.py
commonkit/shell/feedback.py
commonkit/shell/prompts.py
commonkit/shell/scripts.py
commonkit/shell/tables.py
commonkit/shell/variables.py
commonkit/strings/__init__.py
commonkit/strings/library.py
commonkit/types/__init__.py
commonkit/types/library.py
commonkit/versions/__init__.py
commonkit/versions/constants.py
commonkit/versions/library.py
commonkit/versions/utils.py
commonkit/watchers/__init__.py
commonkit/watchers/library.py
python_commonkit-1.14.1.dist-info/LICENSE.txt
python_commonkit-1.14.1.dist-info/METADATA
python_commonkit-1.14.1.dist-info/WHEEL
python_commonkit-1.14.1.dist-info/top_level.txt
python_commonkit-1.14.1.dist-info/RECORD
