Metadata-Version: 2.1
Name: python-commonkit
Version: 1.14.1
Summary: A collection of common resources and utilities to supercharge Python development.
Home-page: https://develmaycare.com/products/python/commonkit/
Download-URL: https://github.com/develmaycare/python-commonkit
Author: Shawn Davis
Author-email: shawn@develmaycare.com
Project-URL: Documentation, https://docs.develmaycare.com/en/python-commonkit/latest/
Project-URL: Source, https://github.com/develmaycare/python-commonkit/
Project-URL: Tracker, https://github.com/develmaycare/python-commonkit/issues/
Classifier: Development Status :: 5 - Production/Stable
Classifier: Environment :: Console
Classifier: Intended Audience :: Developers
Classifier: License :: OSI Approved :: BSD License
Classifier: Operating System :: OS Independent
Classifier: Programming Language :: Python
Classifier: Programming Language :: Python :: 3
Classifier: Programming Language :: Python :: 3.6
Classifier: Programming Language :: Python :: 3.7
Classifier: Topic :: Software Development :: Libraries :: Python Modules
License-File: LICENSE.txt
Requires-Dist: six
Provides-Extra: all
Requires-Dist: beautifulsoup4 ; extra == 'all'
Requires-Dist: colorama ; extra == 'all'
Requires-Dist: jinja2 ; extra == 'all'
Requires-Dist: pygments ; extra == 'all'
Requires-Dist: SQLAlchemy ; extra == 'all'
Requires-Dist: tabulate ; extra == 'all'
Requires-Dist: unidecode ; extra == 'all'
Provides-Extra: database
Requires-Dist: SQLAlchemy ; extra == 'database'
Provides-Extra: mssql
Requires-Dist: pyodbc ; extra == 'mssql'
Requires-Dist: SQLAlchemy ; extra == 'mssql'
Provides-Extra: oracle
Requires-Dist: cx-Oracle ; extra == 'oracle'
Requires-Dist: SQLAlchemy ; extra == 'oracle'
Provides-Extra: pgsql
Requires-Dist: psycopg2-binary ; extra == 'pgsql'
Requires-Dist: SQLAlchemy ; extra == 'pgsql'
Provides-Extra: shell
Requires-Dist: colorama ; extra == 'shell'
Requires-Dist: tabulate ; extra == 'shell'
Provides-Extra: strings
Requires-Dist: beautifulsoup4 ; extra == 'strings'
Requires-Dist: jinja2 ; extra == 'strings'
Requires-Dist: pygments ; extra == 'strings'
Requires-Dist: unidecode ; extra == 'strings'
